python_zo/__init__.py
python_zo/classes.py
python_zo/filters.py
python_zo/lib.py
python_zo-0.0.45.data/scripts/zo
python_zo-0.0.45.dist-info/METADATA
python_zo-0.0.45.dist-info/WHEEL
python_zo-0.0.45.dist-info/top_level.txt
python_zo-0.0.45.dist-info/RECORD
