Metadata-Version: 2.1
Name: python-zo
Version: 0.0.45
Home-page: https://github.com/S-YOU/zo
Download-URL: https://github.com/S-YOU/zo/tarball/master
Author: S-YOU
Author-email: S-YOU@users.noreply.github.com
Requires-Dist: jinja2 (~=3.1.2)
